{"units": [{"id": "u1", "type": "observation", "verb": "granted", "content": "US Patent 7,962,495 B2 was granted to Palantir Technologies on 14 June 2011", "intensity": 0.9, "depends_on": []}, {"id": "u2", "type": "inference", "verb": "anticipates", "content": "The patent anticipates measurer-as-entity under an ontology layer", "intensity": 0.8, "depends_on": ["u1"]}, {"id": "u3", "type": "observation", "verb": "retains", "content": "Claim 12 retains measurer-as-entity specifically bound to the mechanism-1 marker-propagation dependency-graph side", "intensity": 0.7, "depends_on": ["u1", "u2"]}, {"id": "u4", "type": "observation", "verb": "excludes", "content": "Claim 1 and claim 13 ontology disclaimer explicitly excludes an object-type or property-type registry", "intensity": 0.8, "depends_on": ["u1"]}, {"id": "u5", "type": "evaluative", "verb": "tightened", "content": "The exclusion of object-type or property-type registry was tightened in version 6.2", "intensity": 0.6, "depends_on": ["u4"]}, {"id": "u6", "type": "observation", "verb": "specifies", "content": "The relevant specification detail is located at section 4.15", "intensity": 0.4, "depends_on": ["u1"]}]}